{"title":"Yuusha-kei ni Shosu – Anime tem anuncio de 2º temporada e adaptação em Jogo","path":"/2026/03/yuusha-kei-ni-shosu-anime-tem-anuncio-de-2o-temporada-e-adaptacao-em-jogo/","site":"https://www.intoxianime.com","atUri":"at://did:plc:kcr36myzohzce2h5ejhvbmea/site.standard.document/3mi4wmvionzw2","publishedAt":"2026-03-28T13:41:45Z","tags":"notícias;Yuusha-kei ni Shosu: Choubatsu Yuusha 9004-tai Keimu Kiroku (Sentenced to Be a Hero: The Prison Records of Penal Hero Unit 9004);Yuusha-kei ni Shosu – Anime tem anuncio de 2º temporada e adaptação em Jogo;IntoxiAnime"}