{"title":"Reform has been warned that defecting Tories will damage its brand – and the first evidence is in","path":"/2026/02/19/reform-has-been-warned-that-defecting-tories-will-damage-its-brand-and-the-first-evidence-is-in/","site":"https://www.europeans.today","atUri":"at://did:plc:sfdxwudsccuq5igucmo4kc43/site.standard.document/3mfaw7r2kxbf2","publishedAt":"2026-02-19T01:14:00Z","tags":"hastens the demise;Reform is tying its image;Recent figures from _YouGov_;also shows;Who is defecting to Reform UK?;Reform UK's polling surge and the Tory response;How Reform UK and Conservative voters compare;Can Reform UK really replace the Tories?;Nigel Farage’s plan to professionalise Reform UK;Farage predicts more Tory defections;The impact of Tory defectors on Reform brand"}