{"title":"Ηράκλειο : ΑΣΑΦΙ – Κείμενο Σχετικά με το Έγκλημα στη Χίο","path":"/?p=48310","site":"https://candiaalternativa.info","atUri":"at://did:plc:n746clejbewiukrzvmq2dqvg/site.standard.document/3me5nsetvprw2","publishedAt":"2026-02-05T18:40:04Z","tags":"ΑΝΑΔΗΜΟΣΙΕΥΣΕΙΣ;ΑΝΑΚΟΙΝΩΣΕΙΣ;ΑΡΘΡΑ;ΤΟΠΙΚΑ ΝΕΑ-ΗΡΑΚΛΕΙΟ;15 ΜΕΝΑΣΤΕς ΝΕΚΡΟΊ ΣΤΗΝ Χίο;αλληλεγγύη;αντιρατσισμός;καλεσμα;Καταστολή;Κείμενο Σχετικά με το Έγκλημα στη Χίο;Μετανάστες;μετανάστες-πολιτικοί πρόσφυγες;Continue reading \"Ηράκλειο : ΑΣΑΦΙ – Κείμενο Σχετικά με το Έγκλημα στη Χίο\""}