{"title":"Oroscopo del giorno Domenica, 5 Aprile 2026","path":"/oroscopo-del-giorno-domenica-5-aprile-2026/","site":"https://siwa.luxe","atUri":"at://did:plc:jzftw5g7yhkdpzeg4wnxai7p/site.standard.document/3mipis3xmymu2","publishedAt":"2026-04-05T00:31:41Z","tags":"Ariete;Leggi l'oroscopo completo del segno Ariete;Toro;Leggi l'oroscopo completo del segno Toro;Gemelli;Leggi l'oroscopo completo del segno Gemelli;Cancro;Leggi l'oroscopo completo del segno Cancro;Leone;Leggi l'oroscopo completo del segno Leone;Vergine;Leggi l'oroscopo completo del segno Vergine;Bilancia;Leggi l'oroscopo completo del segno Bilancia;Scorpione;Leggi l'oroscopo completo del segno Scorpione;Sagittario;Leggi l'oroscopo completo del segno Sagittario;Capricorno;Leggi l'oroscopo completo del segno Capricorno;Acquario;Leggi l'oroscopo completo del segno Acquario;Pesci;Leggi l'oroscopo completo del segno Pesci"}