{"title":"Jammu and Kashmir Legislative Assembly Announces Election Schedule for Financial Committees","path":"/2026/03/30/jammu-and-kashmir-legislative-assembly-announces-election-schedule-for-financial-committees/","site":"https://thechenabtimes.com","atUri":"at://did:plc:yvpkwzscqadwgkjjwcpe36s2/site.standard.document/3mibllvovygs2","publishedAt":"2026-03-30T11:37:08Z","tags":"Jammu and Kashmir;abdul rahim rather;Bilal Ahmed Bhat;Election Schedule;Financial Committees Election;Jammu and Kashmir Legislative Assembly"}