{"title":"HGTV pulls “Rehab Addict” from its platforms after video emerges of star Nicole Curtis using racial slur","path":"/hgtv-pulls-rehab-addict-after-video-emerges-star-nicole-curtis-using-slur-11905177","site":"https://ew.com","atUri":"at://did:plc:6rzq64c4u5swi25ppvq3ckav/site.standard.document/3mentjtpif6f2","publishedAt":"2026-02-12T02:58:13Z","tags":"News;Reality TV;TV Genres;TV;HGTV;TV Development;TV Industry;Celebrity Feuds & Controversies;Celebrities & Creators;Reality TV Stars;Entertainment Industry Roles"}