{"title":"Sources: recently the DHS has sent hundreds of administrative subpoenas, which do not need a judge's approval, to tech firms to identify people critical of ICE (New York Times)","path":"/260213/p22#a260213p22","site":"http://www.techmeme.com","atUri":"at://did:plc:avkh7zze5iapdkk6naaunrjn/site.standard.document/3mesm3zvpxeo2","publishedAt":"2026-02-14T04:20:01Z","tags":"New York Times;Sources: recently the DHS has sent hundreds of administrative subpoenas, which do not need a judge's approval, to tech firms to identify people critical of ICE"}