{"title":"Google expands Quick Share support with AirDrop to the Pixel 9, 9 Pro, 9 Pro XL, and 9 Pro Fold, after launching it for Pixel 10 in November 2025 (Abner Li/9to5Google)","path":"/260218/p34#a260218p34","site":"http://www.techmeme.com","atUri":"at://did:plc:avkh7zze5iapdkk6naaunrjn/site.standard.document/3mf5izivtdza2","publishedAt":"2026-02-18T15:40:01Z","tags":"9to5Google;Google expands Quick Share support with AirDrop to the Pixel 9, 9 Pro, 9 Pro XL, and 9 Pro Fold, after launching it for Pixel 10 in November 2025"}