{"title":"おにぎりを大量生産できる便利グッズがめちゃくちゃいい！｜2026年2月（3週目）の編集部が買ってよかったもの","path":"/entry/2026/02/20/103000","site":"https://soredoko.jp","atUri":"at://did:plc:ms46tadpbnexczc32wnampz5/site.standard.document/3mfco54iqj6k2","publishedAt":"2026-02-20T01:30:00Z","tags":"楽天ビック;富士パックス おにぎり達人 おにぎり型 6穴 ブラック;楽天で見る;富士パックス おにぎり型 簡単 便利 おむすび 型 6穴 おにぎりメーカー 日本製 おにぎり達人 ライスボールメーカー おにぎらず 押し型 マドーレ 耐熱耐冷 高耐久 MAXブラック;富士パックス販売 おにぎり仙人 ホワイト;富士パックス販売(Fujipacks Hanbai) 日本製！ 一度におにぎりを6個作れる おにぎり型『 おにぎり仙人 』 ホワイト;富士パックス販売 マドーレ グリーン;富士パックス販売(Fujipacks Hanbai) おにぎり型 簡単 便利 おむすび 6穴 おにぎりメーカー 日本製 おにぎり達人 ライスボールメーカー おにぎらず 押し型 マドーレ グリーン;X（Twitter）を見る;Instagramを見る"}