{"title":"Celebrating Black Futures at the Vancouver Art Gallery","path":"/2026/02/05/celebrating-black-futures-at-the-vancouver-art-gallery/?utm_source=rss&utm_medium=rss&utm_campaign=celebrating-black-futures-at-the-vancouver-art-gallery","site":"https://myvancity.ca","atUri":"at://did:plc:jfmfk45dk67zzfvjimseq5pf/site.standard.document/3me67nubf3v22","publishedAt":"2026-02-05T20:19:09Z","tags":"Arts and Culture;Events;B.C. Premiere Screening;Black Is Beautiful;Celebrating Black Futures;Centre for Global Asias;Enemy Alien: Tamio Wakayama;film;Freedom Summer;Indigenous Art from the Collection;Memory and Social Justice;Muhammad Ali;Nina Simone;Performance;photography;Stevie Wonder;The Black Arts Centre;The Kwame Brathwaite Story;Tickets;Vancouver Art Gallery;Vancouver International Film Festival;VIFF Centre;Writing Workshop;Read more;Celebrating Black Futures at the Vancouver Art Gallery;My VanCity"}