{"title":"Narón ya tiene la mejor tapa de Entroido: A Serra se impone con una reinvención del cocido gallego","path":"/naron-ya-tiene-la-mejor-tapa-de-entroido-a-serra-se-impone-con-una-reinvencion-del-cocido-gallego/","site":"https://ferrol360.es","atUri":"at://did:plc:r23bquz476nqn7zgsuy3qwbg/site.standard.document/3mh6rruhg4wi2","publishedAt":"2026-03-16T11:39:35Z","tags":"Actualidad;Ferrolterra;Gastronomía;Narón;Narón ya tiene la mejor tapa de Entroido: A Serra se impone con una reinvención del cocido gallego;Ferrol 360"}