{"title":"[SweetSub&VCB-Studio] 物怪剧场版：第二章 火鼠 / Mononoke: The Ashes of Rage / 劇場版モノノ怪 火鼠 10-bit 1080p HEVC BDRip [MOVIE Fin]","path":"/topics/view/712743_SweetSub_VCB-Studio_Mononoke_The_Ashes_of_Rage_10-bit_1080p_HEVC_BDRip_MOVIE_Fin.html","site":"http://share.dmhy.org","atUri":"at://did:plc:kvn5s4s4kvmv7niucm25tqwp/site.standard.document/3me656424nf22","publishedAt":"2026-02-06T04:41:38Z","tags":"動畫;https://vcb-s.com/archives/14331;https://vcb-s.com/archives/14331;https://vcb-s.com/archives/16986"}