{"title":"Photos/Review: Opeth & Katatonia cast midwinter gloom in Detroit – 2/10/2026","path":"/photos/photos-review-opeth-katatonia-cast-midwinter-gloom-in-detroit-2-10-2026?utm_source=rss&utm_medium=rss&utm_campaign=photos-review-opeth-katatonia-cast-midwinter-gloom-in-detroit-2-10-2026","site":"https://metalinsider.net","atUri":"at://did:plc:66pjquppkvbxtuwiriavevjx/site.standard.document/3mfaqpfqkhuu2","publishedAt":"2026-02-19T19:41:52Z","tags":"Photos;Reviews;Katatonia;Opeth;Photos/Review: Opeth & Katatonia cast midwinter gloom in Detroit – 2/10/2026;Metal Insider"}