{"title":"This Laid-Back Design Trick Lets the Outdoors Do the Work","path":"/jenni-kayne-pacific-natural-everything-book-launch-37539630?utm_source=RSS&utm_medium=feed&utm_campaign=Category%2FChannel%3A+main","site":"https://www.apartmenttherapy.com","atUri":"at://did:plc:e7yjrafo6lu7imrb7iiohklv/site.standard.document/3mf3kyqzlivl2","publishedAt":"2026-02-17T20:30:00Z","tags":"Decorating;decor & accessories;decorating;ideas & inspiration;product module;product text link;styles & trends;windows;**READ MORE...**"}