{"title":"Easter Egg Hunts and Best Things To Do with Kids in Orlando in April 2026, According to MP Editors","path":"/things-to-do-in-orlando-april-kids-families-easter","site":"https://mommypoppins.com","atUri":"at://did:plc:pzjfsjcn2525fxtdfgsv5rr2/site.standard.document/3mib6ovsyd4i2","publishedAt":"2026-03-29T00:00:00Z","tags":"Spring Fever in the Garden;Spring Fiesta in the Park;Lake County Fair;Egg-citing Easter Egg Hunts in Orlando;Spring Fun Guide;Egg Ocoee Helicopter Egg Drop;Hippity Hop Adventure at Central Florida Zoo;Tour of Destruction at Orlando Speed World;Firefly Nights at Blue Spring State Park;Read more."}