{"title":"Eugene Onegin","path":"/eugene-onegin/","site":"https://www.parisupdate.com","atUri":"at://did:plc:fnebf4u55tpaajqvt2is4tzi/site.standard.document/3mehxmxs6m7b2","publishedAt":"2026-02-09T09:53:41Z","tags":"Music;Alexander Tsymbalyuk;Annemarie Woods;Bogdan Volkov;Boris Pinkhasovich;Elena Zaremba;Eugene Onegin;Eugene Onegin Palais Garnier Paris;Marvic Monreal;Michael Levine;Opéra National de Paris;opera review;Palais Garnier;Paris opera;Peter Bronder;Ralph Fiennes;Ruzan Mantashyan;Semyon Bychkov;show;Sophie Laplane;Susan Graham;Paris Update"}