{"title":"صدارت- حذف خادمان از صحنه سیاسی و محدود کردن آن‌ها در برقراری ارتباط با مردم","path":"/2026/02/08/14246/","site":"https://alisedarat.com","atUri":"at://did:plc:nfxp4nkrk3mhvzzv6zfttkmr/site.standard.document/3med3y4qxylu2","publishedAt":"2026-02-07T22:01:57Z","tags":"بنی‌صدر;تا بماند در خاطری...تا بگیریم درسی;صدارت، علی;نوشتارها;کودتای خرداد ۱۳۶۰;آزادی;ابوالحسن بنی صدر;ابوالحسن بنیصدر;ابوالحسن بنی‌صدر;استقلال;افشاگری;ایران;بنی صدر;بنیصدر;حق;حق اطلاع‌رسانی;حق اطلاع‌یابی;حق مطلع شدن;حق مطلع کردن;حقوق;حقوق بشر;حقوق بین‌المللی;حقوق شهروندی;حقوق طبیعت;حقوق ملی;حقوق‌مدار;حق‌وند;خودانگیختگی;خیانت;صدارت;علی صدارت;وجدان تاریخی;وژدان تاریخی"}