{"title":"„A zenei helyszínek vegzálása nem csökkenti érdemben a drogfogyasztást” – több mint ötven koncerthelyszín adott ki közös nyilatkozatot","path":"/kultura/2026/02/08/pecsi-est-razzia-drog/","site":"https://24.hu","atUri":"at://did:plc:l35p73eu3aao2p5vikbjlqtx/site.standard.document/3mefg2yaw4zy2","publishedAt":"2026-02-08T20:02:42Z","tags":"Kultúra;drog;horváth lászló;pécsi est;razzia;szórakozóhely;„A zenei helyszínek vegzálása nem csökkenti érdemben a drogfogyasztást” – több mint ötven koncerthelyszín adott ki közös nyilatkozatot;24.hu"}