{"title":"Digital Independence Day – Der digitale Unabhängigkeitstag","path":"/digital-independence-day-der-digitale-unabhaengigkeitstag/","site":"https://bunte-kuechenabenteuer.de","atUri":"at://did:plc:gscj7ztkdw2atn7njxsflpft/site.standard.document/3mesp5sgafbh2","publishedAt":"2026-02-14T09:23:29Z","tags":"Blogbeitrag;DigitalIndependenceDay;DigitalerUnabhängigkeitstag;Foodblog;DID (**D** igital **I** ndependence **D** ay) oder DUT (**D** igitaler **U** nabhängigkeits**t** ag);https://di.day;auf der Webseite"}