{"title":"Monday's Friday Reads for 30 March","path":"/mondays-friday-reads-for-30-march/","site":"https://londonreconnections.com","atUri":"at://did:plc:ay3ydd4j2iudyy5wjew7sbbj/site.standard.document/3micqolbuw3d2","publishedAt":"2026-03-30T01:00:10Z","tags":"East London’s Beam Park C2C railway station finally approved;West Ashfield: Video;Two Australian states offer free public transport;Belgrade’s first metro line will be delivered by Alstom;A new opportunity for congestion pricing, before AVs flood"}