{"title":"$LIBRA: quién es Orlando Rodolfo Mellino, el “jubilado” que recibió un millón de dólares de Hayden Davis","path":"/2026/02/17/libra-quien-es-orlando-rodolfo-mellino-el-jubilado-que-recibio-un-millon-de-dolares-de-hayden-davis/","site":"https://noticiaslainsuperable.com.ar","atUri":"at://did:plc:gxy735lsorkcgbjlaqtdw6cd/site.standard.document/3mf4yxmbeisq2","publishedAt":"2026-02-17T19:01:40Z","tags":"Judiciales;caso $LIBRA;criptoestafa;Hayden Davis;investigación judicial;Javier Milei;Lavado de Dinero;Orlando Rodolfo Mellino;quien es;USDT;Más"}