{"title":"Federación Venezolana de Baloncesto anuncia convocados para clasificatorio al Mundial 2027","path":"/2026/02/venezuela-anuncia-convocados-para-el-clasificatorio-al-mundial/","site":"https://www.elnacional.com","atUri":"at://did:plc:fuzd5dd7bkcktoqfb6f2fqrh/site.standard.document/3mfa2sdsns6s2","publishedAt":"2026-02-19T14:28:55Z","tags":"Baloncesto;Deportes;convocados;Mundial Qatar 2027;Venezuela;Federación Venezolana de Baloncesto anuncia convocados para clasificatorio al Mundial 2027;EL NACIONAL"}