{"title":"「Lenovo Xiaoxin Pad 2025」がセール価格で約1.6万円に！Dimensity 6300と4スピーカー搭載など高コスパタブレット","path":"/sale-info/111091/","site":"https://daily-gadget.net","atUri":"at://did:plc:vn3ywcfplxvmvt7etydvaipp/site.standard.document/3mh63fnojeea2","publishedAt":"2026-03-16T08:00:48Z","tags":"セール情報;セール情報（AliExpress）;AliExpress;Lenovo;Xiaoxin Pad 2025;「Lenovo Xiaoxin Pad 2025」がセール価格で約1.6万円に！Dimensity 6300と4スピーカー搭載など高コスパタブレット;デイリーガジェット;「ALLDOCUBE iPlay 70 mini Ultra」が約3.3万円で格安セールに！Snapdragon 7+ Gen3搭載で144Hz駆動の小型タブレット;「Lenovo Legion Y700 2025 Gen4」が約5.8万円で格安セールに！Snapdragon 8 Elite搭載 & 165Hz駆動の希少なハイエンド8インチタブ;Snapdragon 8 Elite搭載「OnePlus Pad 3」がセール価格で8.2万円に！バイパス充電＆リモート接続も可能なハイエンドタブがお買い得"}