{"title":"Hands Off Ehsan Ali and the Awami Action Committee: International Day of Action on April 2!","path":"/hands-off-ehsan-ali-and-the-awami-action-committee-international-day-of-action-on-april-2/","site":"https://communistusa.org","atUri":"at://did:plc:prykkqvrlsh5cs4fjjb5i44i/site.standard.document/3micaqjfe4nv2","publishedAt":"2026-03-30T15:00:47Z","tags":"Events & Reports;Highlights;Pakistan;Solidarity Appeal;Hands Off Ehsan Ali and the Awami Action Committee: International Day of Action on April 2!;Revolutionary Communists of America"}