{"title":"One Pilot Rescued After U.S. Jet Downed Inside Iran for First Time, Search Continues for Another: Reports","path":"/one-u-s-pilot-rescued-after-irgc-shot-down-one-u-s-fighter-jet-over-iran-reports/","site":"https://www.eurasiantimes.com","atUri":"at://did:plc:zrlt7lbxqdlahanilc2hlimf/site.standard.document/3mim64lb4a3c2","publishedAt":"2026-04-03T16:14:50Z","tags":"Americas;World;One Pilot Rescued After U.S. Jet Downed Inside Iran for First Time, Search Continues for Another: Reports;EURASIAN TIMES"}