{"title":"“Riot apparently just learned today that the FGC is broke”: 2XKO’s focus on expensive cosmetics backfired immensely","path":"/news-fgc-dont-buy-2xko-skins/","site":"https://www.escapistmagazine.com","atUri":"at://did:plc:vq26ms46fdyemijyk2ftxjbo/site.standard.document/3meoqpynpfx42","publishedAt":"2026-02-12T00:02:25Z","tags":"Esports;FGC;Opinion;2XKO;Featured;“Riot apparently just learned today that the FGC is broke”: 2XKO’s focus on expensive cosmetics backfired immensely;The Escapist"}