{"title":"Dragon Quest VII Reimagined quer alcançar novos jogadores sem perder a essência, explica produtor","path":"/voxel/503439-dragon-quest-vii-reimagined-quer-alcancar-novos-jogadores-sem-perder-a-essencia-explica-produtor.htm","site":"https://www.tecmundo.com.br","atUri":"at://did:plc:ulfbtqn2ybcgbzf27z75qrvu/site.standard.document/3me5fue4blc42","publishedAt":"2026-02-05T20:15:16Z","tags":"Voxel;Review: Dragon Quest VII Reimagined resgata clássico em RPG charmoso, mas longe de ser perfeito | Voxel"}