{"title":"Galaxy S26: Samsung confirma data do Unpacked 2026; saiba o que esperar","path":"/produto/410323-galaxy-s26-samsung-confirma-data-do-unpacked-2026-saiba-o-que-esperar.htm","site":"https://www.tecmundo.com.br","atUri":"at://did:plc:ulfbtqn2ybcgbzf27z75qrvu/site.standard.document/3mek7s6okylx2","publishedAt":"2026-02-10T23:17:22Z","tags":"Produto;Ver essa foto no Instagram;Um post compartilhado por TecMundo (@tecmundo);novos topos de linha são especulados há meses;fones de ouvido Galaxy Buds 4 e Buds 4 Pro também devem aparecer no evento;destaque do evento deve ser a One UI 8.5;nova versão da Bixby com inteligência artificial (IA) da Perplexity"}