{"title":"Home office: 88 vagas para trabalho remoto [29/03]","path":"/mercado/411982-home-office-88-vagas-para-trabalho-remoto-2903.htm","site":"https://www.tecmundo.com.br","atUri":"at://did:plc:ulfbtqn2ybcgbzf27z75qrvu/site.standard.document/3mia6grfeson2","publishedAt":"2026-03-29T22:00:00Z","tags":"The BRIEF;Remotar;Advogado Junior;Analista Financeiro;Analista Fiscal;Analista Jurídico;Analista Pleno de Faturamento;Analista de Talent Acquisition;Assistente Fiscal | Temporário;Auxiliar Administrativo;Coordenador Financeiro;Coordenador Jurídico;Estágio Administrativo;Estágio Administrativo - Direito;Estágio Financeiro;Estagiário de Legalização;Estagiário de Operações;Estágio em Recrutamento;Estagiária (o) de RH;Gerente de Estratégia Econômico - Tributária e Viabilidade;Recrutador Júnior;Agente de Retenção de Clientes (Vendas);Analista de Customer Success;Analista de Marketing de Produto Pleno;Analista de Mídia III - Performance;Analista de Negócios Júnior;Assessor(a) de Atendimento e Vendas para Clientes VIP;Assistente Comercial;Coordenadora de Copywriting;Estágio em Atendimento ao Cliente;Estágio em Pré-Vendas / Comercial;Gerente de Contas - Marketing Digital;Gerente de Marketing;Gestor(a) de Tráfego Junior;Pessoa coordenadora comercial | SDR;Redator(a) de Conteúdo Sênior (Narrativas e Estratégia);Social Mídia;Social Media - Sênior;Supervisor(a) de Sucesso do Cliente;Vendedor;Virtual Assistant - Sales - Cleaning Services;Chefe de Criação;Designer;Designer Gráfico;Designer Gráfico Digital Júnior | Pleno;Designer Instrucional;Design Manager;Designer Pleno;Diretor(a) de Arte;Editor de Vídeo Pleno - Motion & IA;Especialista em Design Criativo;Estágio em Projetos Gráficos (Identidade Visual);Motion Designer (Diretor de Arte);Motion Designer Senior;UI/Web Designer;UX Designer;UX Designer Sênior;UX/UI Designer Pleno;UI/UX Designer Sênior;Analista de Produtos Sênior;Especialista em Projetos;Estagiário de Produtos;Estagiário de Projetos;Gerente de Projetos Pleno;Product Lead;Product Manager;Product Manager - Generosity;Product Manager Sênior;Product Manager Sr;Product Owner;Product Owner Pleno;Senior Software Product Manager;Supervisor de Performance;Technical Product Manager;Analista Pleno de Prevenção à Fraude;Backend Engineer- Python/Django;Desenvolvedora Backend Pleno;Desenvolvedor(a) Back-End Sênior (Python);Desenvolvedor Junior - Projetos;Desenvolvedor(a) Kotlin/React Especialista II;Desenvolvedor(a) Mobile IOS;Desenvolvedor(a) Sênior - Golang e Vue.js;Engenheiro(a) de Software Front-end Sr;Estagiário(a) de Tecnologia da Informação;Front-end (React);QA Engineer;Senior Backend Software Engineer (Python);Senior Full Stack;Tech Manager"}