{"title":"İsrail ordusu: Gazze Şeridi’ne kaçak mal sokulması sorunu güvenliğimiz için büyük bir tehdit","path":"/node/772431/d%C3%BCnya/i%CC%87srail-ordusu-gazze-%C5%9Feridi%E2%80%99ne-ka%C3%A7ak-mal-sokulmas%C4%B1-sorunu-g%C3%BCvenli%C4%9Fimiz-i%C3%A7in-b%C3%BCy%C3%BCk","site":"https://www.indyturk.com","atUri":"at://did:plc:v6hv4xoilbya2asvp47entc2/site.standard.document/3meajryk7tqs2","publishedAt":"2026-02-06T14:46:28Z","tags":"_Şarku'l Avsat'ın_ haberlerine ulaşmak için tıklayın;İsrail;Dünya;news"}