{"title":"Con DT interino y el regreso de Cuevas a La Ciudadela: así llega Chacarita, el rival de San Martín","path":"/nota/1131049/deportes/con-dt-interino-regreso-cuevas-ciudadela-asi-llega-chacarita-rival-san-martin.html","site":"https://www.lagaceta.com.ar","atUri":"at://did:plc:kxscagnvvwphcwbfzsxafacg/site.standard.document/3mimbpifxtpc2","publishedAt":"2026-04-03T12:59:00Z","tags":"Tucumán;Deportes;Fútbol;San Martín de Tucumán;Primera Nacional;Club Atlético Estudiantes;Enrique Bologna;La Ciudadela;Chacarita Juniors;San Martín;Juan Cuevas;Estudiantes de Caseros;Matías Módolo;Cristian Grabinski"}