{"title":"Reader’s Corner: Diary of a Female Lead (Vol. 5), Choking on Love (Vol. 4), and A Reincarnated Witch Spells Doom (Vol. 7)","path":"/2026/03/31/readers-corner-march-31-2026/","site":"https://beneaththetangles.com","atUri":"at://did:plc:3chvxhb4euoyv6axrjhe4fdb/site.standard.document/3mifp3wxp3z62","publishedAt":"2026-03-31T13:00:00Z","tags":"Reader's Corner;a reincarnated witch spells doom;Almark;anime;Choking on Love;Diary of a Female Lead;Diary of a Female Lead: Shujinkou Nikki;Fool Night;Glasses with a Chance of Delinquent;Honeko Akabane's Bodyguards;manga.;ruridragon;shoujo;shoujo manga;Tsumiki Ogami's Not-So-Ordinary Life;Read More Reader’s Corner: Diary of a Female Lead (Vol. 5), Choking on Love (Vol. 4), and A Reincarnated Witch Spells Doom (Vol. 7)"}