{"title":"Community push intensifies to free MySQL from Oracle’s control amid stagnation fears","path":"/article/4134406/community-push-intensifies-to-free-mysql-from-oracles-control-amid-stagnation-fears-2.html","site":"https://www.cio.com","atUri":"at://did:plc:qz6ohvpdsdvv5kniizyfz25y/site.standard.document/3mf7fumxfh7y2","publishedAt":"2026-02-19T09:39:13Z","tags":"Data Management, Databases, MySQL, Relational Databases;open letter;MySQL’s development velocity;Vadim Tkachenko;Stephanie Walter;Tony Baer;2025 Stack Overflow survey;Julia Vural;blog post;Frederic Descamps;moved to the MariaDB Foundation"}