{"title":"Still in Love","path":"/4659267","site":"http://www.zerochan.net","atUri":"at://did:plc:4yfuzjzcdeclcb5jyr5n7rgh/site.standard.document/3meyuutex37m2","publishedAt":"2026-02-16T20:22:09.11Z","tags":"Female;Fanart;Dress;Black Dress;Long Hair;Brown Hair;Red Eyes;Ribbon;Gloves;Blush;Shoes;Tail;Pink Ribbon;Bow (Fashion);Jewelry;Ring;Bracelet;Headdress;Kemonomimi;White Background;Personification;Pixiv;Nail Polish;Solo;Standing;Smile;Simple Background;Black Gloves;Red Nails;Fanart from Pixiv;Looking At Camera;Long Gloves;Light Background;Full Body;Animal (Personification);Bare Knees;Umamimi;Black Footwear;Asymmetrical Armwear;Black\n\tHandwear;Halterneck;Exposed Shoulders;Uma Musume: Pretty Derby;Mobile Wallpaper;Bails;Horse Tail;Long Black\n\tGloves;Still in Love;Horse (Personification)"}