{"title":"Three of our all-time favourite cycling helmets have been heavily discounted – See for yourself why our expert rated these lids as some of the best","path":"/deals/three-of-our-all-time-favourite-cycling-helmets-have-been-heavily-discounted-see-for-yourself-why-our-expert-rated-these-lids-as-some-of-the-best","site":"https://www.cyclingweekly.com","atUri":"at://did:plc:xwlaf2app6wwpx5pwfbnqtgg/site.standard.document/3mequst7xh3z2","publishedAt":"2026-02-13T13:34:11Z","tags":"Deals and Bargains"}