{"title":"O que aconteceu com Ludmilla? Especialistas fazem alerta sobre novo rosto da cantora:","path":"/famosos/o-que-aconteceu-com-ludmilla-especialistas-fazem-alerta-sobre-novo-rosto-da-cantora.phtml","site":"https://www.maisnovela.com.br","atUri":"at://did:plc:j4flwmslysr2wc22jx5nhj2n/site.standard.document/3miorwprxs2a2","publishedAt":"2026-04-04T17:00:23Z","tags":"Famosos;Cirurgia;Ludmilla;plástica;procedimento;rosto;O que aconteceu com Ludmilla? Especialistas fazem alerta sobre novo rosto da cantora:;Mais Novela"}