{"title":"Japan’s Brokerage War: Rakuten Lowers Entry Barriers, Webull Eyes Quant Traders, and Woodstock Cracks the Onboarding Code","path":"/japans-brokerage-war-rakuten-lowers-entry-barriers-webull-eyes-quant-traders-and-woodstock-cracks-the-onboarding-code/","site":"https://www.fintechobserver.com","atUri":"at://did:plc:mwi7gtnakn7adnxflkv4wt3y/site.standard.document/3miqjrapjdh72","publishedAt":"2026-04-05T10:22:43Z","tags":"Woodstock brings “Robinhood Moment” to Japan with Zero-Fee, 24-Hour US Stock Trading LaunchWoodstock has completed a sweeping overhaul of its service model, introducing 24-hour trading capability and completely eliminating transaction fees for US stocks. The announcement was made during a media briefing held in Tokyo, where Woodstock CEO Brian Yun outlined the company’s aggressive strategy to capture the burgeoning interest inJapan FinTech ObserverNorbert Gehrke"}