{"title":"L’extrême-gauche tue: c’est maintenant un fait établi. Par Dina Kaplan","path":"/2026/02/15/lextreme-gauche-tue-cest-maintenant-un-fait-etabli-par-dina-kaplan/","site":"https://www.tribunejuive.info","atUri":"at://did:plc:xxoukot4d2rzmnrl6pbyz3jh/site.standard.document/3mewctquzc652","publishedAt":"2026-02-15T07:16:14Z","tags":"Edito;\"L'extrême-gauche tue: c'est maintenant un fait établi\";Dina Kaplan;Quentin;[...];L’extrême-gauche tue: c’est maintenant un fait établi. Par Dina Kaplan;Tribune Juive"}