{"title":"Ichilov lance Ichilov NOW : un parcours d’accès rapide qui commence déjà à la maison vers les urgences d’Ichilov","path":"/2026/03/29/ichilov-lance-ichilov-now-un-parcours-dacces-rapide-qui-commence-deja-a-la-maison-vers-les-urgences-dichilov/","site":"https://www.tribunejuive.info","atUri":"at://did:plc:xxoukot4d2rzmnrl6pbyz3jh/site.standard.document/3miagxeorwk62","publishedAt":"2026-03-29T10:54:50Z","tags":"Israël Défense;Ichilov;Ichilov Now;[...];Ichilov lance Ichilov NOW : un parcours d’accès rapide qui commence déjà à la maison vers les urgences d’Ichilov;Tribune Juive"}