{"title":"Flávio Bolsonaro usa vídeo de inteligência artificial para criticar desfile de escolas de samba em homenagem a Lula","path":"/flavio-bolsonaro-usa-video-de-inteligencia-artificial-para-criticar-desfile-de-escolas-de-samba-em-homenagem-a-lula/","site":"https://www.opiniaoce.com.br","atUri":"at://did:plc:my7vnebpi54yzb7skoygfe4s/site.standard.document/3mezsukfotik2","publishedAt":"2026-02-16T16:21:01Z","tags":"Política;Destaque 3;escolas de samba;Flávio Bolsonaro;inss;Instituto Nacional do Seguro Social;inteligência artificial;Luiz Inácio Lula da Silva;Lula;Recursos Públicos"}