{"title":"High-End-Sensorik aus dem Automotive-Bereich: Der LiDAX Ultra mit 360°-3D-LiDAR und KI-Kamera","path":"/article/3060710/high-end-sensorik-aus-dem-automotive-bereich-der-lidax-ultra-mit-360-3d-lidar-und-ki-kamera.html","site":"https://www.pcwelt.de","atUri":"at://did:plc:lcqnmkieaiknpxjwvmcefo6g/site.standard.document/3mf3ggisz7ak2","publishedAt":"2026-02-17T20:10:30Z","tags":"Smart Gardens;Jetzt den LiDAX Ultra mit High-End-Navigation entdecken;Jetzt den LiDAX Ultra mit High-End-Navigation entdecken;Jetzt den LiDAX Ultra mit High-End-Navigation entdecken;MOVA-Website;Hier mehr erfahren!"}