{"title":"Dank Amazon-Coupon gibt es diesen Bestseller-Beamer mit bis zu 240 Zoll für nur 89,99 Euro","path":"/article/3064110/wielo-smart-beamer-angebot-deal-rabatt-coupon-amazon.html","site":"https://www.pcwelt.de","atUri":"at://did:plc:lcqnmkieaiknpxjwvmcefo6g/site.standard.document/3mf65mgsvtqh2","publishedAt":"2026-02-18T16:59:51Z","tags":"Smart TVs;**Endpreis auf günstige 89,99 Euro sinkt**;**Beliebter Smart-Beamer mit bis zu 240 Zoll dank Coupon für nur 89,99 Euro bei Amazon**;Beliebter Smart-Beamer mit bis zu 240 Zoll dank Coupon für nur 89,99 Euro;**Beliebter Smart-Beamer mit bis zu 240 Zoll dank Coupon für nur 89,99 Euro**;Weitere Beamer ansehen;Alle aktuellen Amazon-Angebote"}