{"title":"Alckmin anuncia regulamentação de salvaguardas em acordos comerciais","path":"/negocios/alckmin-anuncia-regulamentacao-de-salvaguardas-em-acordos-comerciais/","site":"https://www.portalin.com.br","atUri":"at://did:plc:alux2y4pmw5ykgoelzcwch3i/site.standard.document/3mfb5scd5e642","publishedAt":"2026-02-20T03:01:10Z","tags":"IN Business;Acordo Mercosul-UE;Acordos comerciais;Alckmin;Comércio exterior;Salvaguardas;Alckmin anuncia regulamentação de salvaguardas em acordos comerciais;Portal IN - Pompeu Vasconcelos - Balada IN"}