{"title":"Última hora del ataque de Estados Unidos e Israel contra Irán, en directo | Trump amenaza con atacar centrales eléctricas iraníes si el régimen no abre el estrecho de Ormuz en 48 horas","path":"/internacional/2026-03-22/ultima-hora-del-ataque-de-estados-unidos-e-israel-contra-iran-en-directo.html","site":"https://elpais.com","atUri":"at://did:plc:cqdf2dwsxwwu2bpxb4zq5fkc/site.standard.document/3mhn5mb7kkmp2","publishedAt":"2026-03-22T08:31:07Z","tags":"Guerra;Conflictos;Conflicto árabe-israelí;Conflictos armados;Conflictos internacionales;Franja Gaza;Israel;Hamás;Palestina;Oriente Próximo;Ataque contra Irán"}