{"title":"Trump Wants to ‘Take Over’ Elections. These States are Prime Targets.","path":"/2026/03/08/us/politics/trump-elections-fulton-county-ballots.html","site":"https://www.nytimes.com","atUri":"at://did:plc:7nuyhqvd4a6xquezhjhvregv/site.standard.document/3mgkpw7qrrud2","publishedAt":"2026-03-08T14:19:52Z","tags":"United States Politics and Government;Democratic Party;Justice Department;Election Integrity Network;Republican Party;Trump, Donald J;Dhillon, Harmeet;Arizona;Atlanta (Ga);Detroit (Mich);Fulton County (Ga)"}