{"title":"Campeonato Italiano: Assista ao vivo e de graça ao jogo Hellas Verona x Pisa","path":"/345877/campeonato-italiano-assista-ao-vivo-e-de-graca-ao-jogo-hellas-verona-x-pisa/","site":"https://www.tvpop.com.br","atUri":"at://did:plc:zj32h4gz46bsyiskj3kc2kn2/site.standard.document/3me7qeijjt5h2","publishedAt":"2026-02-06T18:44:52Z","tags":"Hoje na TV;Campeonato Italiano;Campeonato Italiano ao vivo;Campeonato Italiano ao vivo e de graça;futebol;futebol ao vivo;futebol ao vivo e de graça;futebol em hd;futebol internacional;hoje na tv;TV Pop;Campeonato Italiano: Assista ao vivo e de graça ao jogo Hellas Verona x Pisa"}