{"title":"NFL: Bad Bunny focuses on unity and culture ahead of historic Super Bowl show","path":"/celebrities/2026/02/06/308879/nfl-bad-bunny-focuses-on-unity-and-culture-ahead-of-historic-super-bowl-show/","site":"https://interaksyon.philstar.com","atUri":"at://did:plc:qhjxjbktvnyqqejo42gj723b/site.standard.document/3me6r3l7kyhm2","publishedAt":"2026-02-06T09:18:25Z","tags":"Celebrities;SuperBowl;SuperbowlLX;Bad Bunny;Debí Tirar Más Fotos;ice;super bowl;Super Bowl 2026;Super Bowl halftime show;Super Bowl LX;Super Bowl LX halftime show;U.S. Immigration and Customs Enforcement;NFL: Bad Bunny focuses on unity and culture ahead of historic Super Bowl show;Interaksyon"}