{"title":"Warum Gespräche scheitern, bevor das erste Wort gesprochen wurde","path":"/2026/02/10/warum-gespraeche-scheitern-bevor-das-erste-wort-gesprochen-wurde/","site":"https://god.fish","atUri":"at://did:plc:u7qw4z4saopq2zg4ll5cxxoj/site.standard.document/3mekumjka4uj2","publishedAt":"2026-02-10T09:42:43Z","tags":"neu;Alte Verletzungen;Beziehungen;Emotionale Altlasten;eskalation;Kommunikation;Konflikte;Kränkung;Psychologie;Psychotherapie;Validierung;Warum Gespräche scheitern, bevor das erste Wort gesprochen wurde;god.fish"}