{"title":"Expert Review: Matata Studio’s MX2-AS Digital Microscope","path":"/mx2-as-digital-microscope-review/","site":"https://thetoyinsider.com","atUri":"at://did:plc:vlzby7sp4suykrfw3whtxghf/site.standard.document/3mf4wz3fwiit2","publishedAt":"2026-02-18T11:00:00Z","tags":"5-7 (Grade School);8+ (Tweens);Educational;Reviews by Age;STEM;Toy Reviews;best toys for older kids;best toys for young kids;great educational toys;Matata Studio;MX2-AS Digital Microscope;toys for 5 year old;Expert Review: Matata Studio’s MX2-AS Digital Microscope;The Toy Insider"}