{"title":"Federal courthouse shooting: San Francisco court security shot a knife-wielding trespasser four times, feds say","path":"/2026/02/19/federal-courthouse-shooting-san-francisco-court-security-shot-a-knife-wielding-trespasser-four-times-feds-say/","site":"https://www.mercurynews.com","atUri":"at://did:plc:hdpykexnujp4btcfqddpgglf/site.standard.document/3mfargbyhed32","publishedAt":"2026-02-19T21:53:13Z","tags":"California News;Crime and Public Safety;Latest Headlines;Local News;News;Bay Area Crime;Crime;Regional"}