{"title":"The New Athenas | by Esmée Streachailt","path":"/the-new-athenas-by-esmee-streachailt/","site":"https://www.medusarising.org","atUri":"at://did:plc:oqiaqcv4fci2tdoadzvntjii/site.standard.document/3mexglkwrbtl2","publishedAt":"2026-02-16T06:33:41Z","tags":"OpDeathEaters;pic.twitter.com/Vc4eUgj1Mr;February 12, 2026;pic.twitter.com/EZtGsXd4qv;February 11, 2026;Epstein Files ExplorerA comprehensive tool for exploring publicly released Epstein case documents and records.Public Record Database;Rude Law Dog (@esghound.com);02/10/2026 03:18:27;Decoding an Unknown Survivor’s Journal - Part 1Trigger Warning: discussion of sexual abuse of a minor and child lossThe Panicked WriterEllie Leonard;relatively dignified violence of Sargon of Akkad;Epstein files photo shows trapdoor opening to water. Here’s its likely purposeSocial media users speculated that the door was used for nefarious purposes related to unproven “ritualistic sacrifice” rumors.Snopes.comEmery Winter;you look at his emails;patriarchy's dark triad;pic.twitter.com/xGMr8TsxqS;February 10, 2026;The Morrígan — The Order of the CrowsThe Morrígan is an ancient Irish goddess of war, battle, prophecy, sovereignty, and otherworld power. While She was worshipped primarily in Iron Age Ireland, the earliest recorded mention of her dates back to 750 BC - however, this is widely believed to be a retelling of much older (oral) stories, aThe Order of the CrowsHome;Journeys in the Mirror-WorldIntroduction: Rape, Power, and the Epstein FilesCulture War BluesJane Clare Jones;WBAI Radio Archives;Manifesto RadMatFem;Contribute Your Brilliance, Goddess!!;@gorgons@medusarising.org;@YourAnonCentral;@AdameMedia;@TheJFreakinC"}