{"title":"[ Etats-Unis ] Tempête à la Commission sur la liberté religieuse : la commissaire Carrie Prejean Boller évincée après ses propos sur le sionisme","path":"/etats-unis-tempete-a-la-commission-sur-la-liberte-religieuse-la-commissaire-carrie-prejean-boller-evincee-apres-ses-propos-sur-le-sionisme/","site":"https://tribunechretienne.com","atUri":"at://did:plc:3gecrfqvhtvuztxvjh5hqu4z/site.standard.document/3menrqnowwty2","publishedAt":"2026-02-12T10:18:35Z","tags":"À la une;Carrie Prejean Boller;Commission sur la liberté religieuse;Etats-Unis;sionisme"}