{"title":"1000 km feletti hatótáv – különleges akkut tesztelnek ebben a villanyautóban","path":"/2026/02/13/1000-km-feletti-hatotav-kulonleges-akkut-tesztelnek-ebben-a-villanyautoban/","site":"https://villanyautosok.hu","atUri":"at://did:plc:3ackcjauy474yl6c3rfc52v3/site.standard.document/3meq4n7pgby52","publishedAt":"2026-02-13T07:02:11Z","tags":"elektromos autó;elektromosautó-akkumulátor;FAW;félig szilárdtest-akkumulátor;Hongqi;Kína;kínai elektromos autó;tesztautó;1000 km feletti hatótáv – különleges akkut tesztelnek ebben a villanyautóban;Villanyautósok;Simon Zsolt"}