{"title":"Movistar Plus+ ha estrenado por sorpresa una de las películas de terror más esperadas","path":"/noticias/operadores/movistar-plus-estrenado-peliculas-terror-mas-esperadas/","site":"https://www.adslzone.net","atUri":"at://did:plc:zfkx2dhqf3sjdalzku4ajvqy/site.standard.document/3mfcwz2zxlaz2","publishedAt":"2026-02-20T19:04:00Z","tags":"estrenos de febrero;usuarios de Movistar Plus+;Suscripción mensual - 9,99 EUR;Oferta anual (2 meses gratis) - 99,90 EUR;Oferta anual Bono Cultural Joven (8 meses gratis) - 39,00 EUR;Sé lo que hicisteis el último verano en Movistar Plus+;como Karate Kid Legends"}