{"title":"Italia – Materiale diagnostico – CARTE TERMICHE VARIE TIPOLOGIE – Asl Ba (scadenza 23/07/2025)","path":"/procedura-8df67cfc-b98d-4d56-9f79-ad5d684062cf/","site":"https://vistagare.it","atUri":"at://did:plc:u77gte2yaalbgh5p3ujdvtvp/site.standard.document/3mgvrydsryqb2","publishedAt":"2026-03-13T01:03:17Z","tags":"Asl Ba;Apparecchiature mediche, prodotti farmaceutici e per la cura personale;Materiali medici;Recipienti e sacche di raccolta, materiale di drenaggio;Materiale diagnostico;Subscribe now"}