{"title":"Italia – Servizi di mensa scolastica – PROCEDURA APERTA PER L'AFFIDAMENTO DEL SE… – Comune di Sant Antioco (scadenza 12/12/2025)","path":"/procedura-f18e4fce-3076-4990-91f5-80b3f063cb35/","site":"https://vistagare.it","atUri":"at://did:plc:u77gte2yaalbgh5p3ujdvtvp/site.standard.document/3mgw2d7zqyux2","publishedAt":"2026-03-13T03:27:17Z","tags":"Comune di Sant Antioco;Servizi alberghieri, di ristorazione e di vendita al dettaglio;Servizi di catering;Servizi di mensa scolastica;Subscribe now"}