{"title":"Programmänderung bei Sat.1: Hat der Sender diese Crime-Serie abgesetzt?","path":"/serien/navy-cis/251927-programmaenderung-sat1-sender-crime-serie-abgesetzt.html","site":"https://www.netzwelt.de","atUri":"at://did:plc:dlpbf6vkn7igcg467qrzeqwo/site.standard.document/3mh5yiluss2v2","publishedAt":"2026-03-16T06:00:00Z","tags":"Sat.1;TV-Show;TV-Serie / Webserie;TV-Sender;Entertainment;Serien;Navy CIS: Episodenguide und Staffeln;Joyn;Neu bei Joyn: Diese Serien-, Show- und Filmhighlights starten im März 2026;FBI: Staffeln und Episodenguide"}