{"title":"RustHeart (Glowmade) [PC –Tork: Prehi Betac Punk [Xbox] – Cancelled] Beta","path":"/2026/03/21/rustheart-glowmade-pc-cancelled/","site":"https://www.unseen64.net","atUri":"at://did:plc:qvj4qho3ifsiqllkqspyweae/site.standard.document/3mhm3j54r5oc2","publishedAt":"2026-03-21T09:30:23Z","tags":"PC / MAC;Action RPG;Adventure;coop;Electronic Arts;Glowmade Ltd.;EA Originals label;nothing as yet been specified;VG24/7;Jonny Hopper;The Iron Giant;Rick and Morty;Tequila Works;WonderWorlds;shared;Danny Whitehouse;LinkedIn profile;King of Meat;RustHeart (Glowmade) [PC – Cancelled];Unseen64: Beta, Cancelled & Unseen Videogames!"}