{"title":"2026 Square Enix Publisher Sale Stars Ben Starr and Matt Mercer Recommending RPGs","path":"/2026-square-enix-publisher-sale-stars-ben-starr-and-matt-mercer-recommending-rpgs/?utm_source=rss&utm_medium=rss&utm_campaign=2026-square-enix-publisher-sale-stars-ben-starr-and-matt-mercer-recommending-rpgs","site":"https://www.siliconera.com","atUri":"at://did:plc:k2znobm2uaoutib2w6ikfith/site.standard.document/3mh7ydtorh5s2","publishedAt":"2026-03-16T21:00:00Z","tags":"News;Nintendo Switch;Nintendo Switch 2;PC;PlayStation 4;PlayStation 5;Xbox One;Xbox Series X;Europe;Japan;North America;Square Enix;retailers like Best Buy;YouTube;Nintendo eShop;PlayStation Store;Xbox Store;Steam;_Final Fantasy XII: The Zodiac Age_;2026 Square Enix Publisher Sale Stars Ben Starr and Matt Mercer Recommending RPGs;Siliconera"}