{"title":"9 “Unexpected” Floral Dresses You’ll Want To Wear Everywhere This Spring","path":"/floral-dresses/","site":"https://www.brit.co","atUri":"at://did:plc:4wm5hzodiixi55kvfix2iomt/site.standard.document/3mgjwcza5eqm2","publishedAt":"2026-03-07T17:00:02Z","tags":"Fashion;Dresses;Floral;Spring style;Spring fashion;Editecom;Style;dress styles;Miranda Priestly;guest attire for a backyard wedding;Abercrombie & Fitch Emerson Puff Sleeve Midi Dress;Reformation Dale Dress;Lisa Says Gah Elizabeth Dress;House Of CB Ysabella Floral Maxi Sundress;Universal Thread Sleeveless Button-Front Smocked Maxi Empire Waist Dress;For Love & Lemons Brigitta Floral Midi Dress;Reformation Yves Knit Mini Dress;Urban Outfitters Tied With A Bow Lace + Ribbon Trim Satin Slip Maxi Dress;Mila Mae Floral Eyelet Fit & Flare Midi Dress;our newsletter"}