{"title":"Final Four Predictions: Who Wins Saturday and Who Reaches the National Championship Game?","path":"/2026/04/final-four-predictions-who-wins-saturday-and-who-reaches-the-national-championship-game/","site":"https://thehoopdoctors.com","atUri":"at://did:plc:tvps2vjqbfhz6kxjtadpquns/site.standard.document/3minccjv7i242","publishedAt":"2026-04-03T23:37:30Z","tags":"NCAA;breakingbar;slider;Final Four Predictions: Who Wins Saturday and Who Reaches the National Championship Game?;The Hoop Doctors"}