{"title":"Windows Update Crashes: Is Microsoft Really to Blame? Insights from Raymond Chen","path":"/windows-update-crashes-is-microsoft-really-to-blame-insights-from-raymond-chen/","site":"https://www.tech2geek.net","atUri":"at://did:plc:isx5m6wiqw7ljr7tlrnkukux/site.standard.document/3miqvz6fsnyg2","publishedAt":"2026-04-05T00:44:00Z","tags":"Windows;KB5079391;Microsoft update problems;Patch Tuesday;PC crash troubleshooting;Raymond Chen blog;system instability;Windows 11;Windows 11 issues;Windows Update crash"}