{"title":"Moradores de Montenegro (RS) se mobilizam contra instalação de aterro às margens do rio Caí","path":"/2026/02/11/moradores-de-montenegro-rs-se-mobilizam-contra-instalacao-de-aterro-as-margens-do-rio-cai/","site":"https://www.brasildefato.com.br","atUri":"at://did:plc:5t3y22t5r2asbdkhnujroekl/site.standard.document/3memdwetpolv2","publishedAt":"2026-02-11T20:24:34Z","tags":"Direitos;meio ambiente;poluição;rio grande do sul;socioambiental;Moradores de Montenegro (RS) se mobilizam contra instalação de aterro às margens do rio Caí;Brasil de Fato"}