{"title":"Que horas estreia o 2º episódio da segunda temporada de Demolidor: Renascido?","path":"/noticias/quando-estreia/que-horas-estreia-o-2o-episodio-da-segunda-temporada-de-demolidor-renascido.phtml","site":"https://cinebuzz.com.br","atUri":"at://did:plc:4bj47cijezuhvvgcrgcpqd6s/site.standard.document/3mid3xwkg7l62","publishedAt":"2026-03-30T13:00:31Z","tags":"Quando estreia?;Séries;TV e Séries;Charlie Cox;Demolidor;Demolidor: Renascido;Jessica Jones;Krysten Ritter;Marvel;Universo Cinematográfico da Marvel"}