{"title":"On recrute des bénévoles motivé·e·s pour le printemps 2026","path":"/2026/03/on-recrute-des-benevoles-motivees-pour-le-printemps-2026/?utm_source=rss&utm_medium=rss&utm_campaign=on-recrute-des-benevoles-motivees-pour-le-printemps-2026","site":"https://www.bretagne-vivante.org","atUri":"at://did:plc:qlfqmuridk5u2tduwzp4ujk3/site.standard.document/3mhmnqwrkrd22","publishedAt":"2026-03-21T07:00:00Z","tags":"Action terrain;On recrute des bénévoles motivé·e·s pour le printemps 2026;Bretagne Vivante"}