{"title":"Lucas Pinheiro Braathen Faz História nos Jogos de Inverno com Ouro Inédito para o Brasil","path":"/forbes-life/2026/02/lucas-pinheiro-braathen-faz-historia-nos-jogos-de-inverno-com-ouro-inedito-para-o-brasil/","site":"https://forbes.com.br","atUri":"at://did:plc:7xn3eh5mdh5vmfy74svufgot/site.standard.document/3metaunpxssf2","publishedAt":"2026-02-14T14:09:16Z","tags":"Forbes Life;Forbes Sport;esporte;medalha;medalha de ouro;olimpíadas de inverno;Lucas Pinheiro Braathen Faz História nos Jogos de Inverno com Ouro Inédito para o Brasil;Forbes Brasil"}