{"title":"Como Repensar a Reserva de Emergência em Tempos de Incerteza na Geopolítica Global?","path":"/forbes-money/2026/03/como-repensar-a-reserva-de-emergencia-em-tempos-de-incerteza-na-geopolitica-global/","site":"https://forbes.com.br","atUri":"at://did:plc:7xn3eh5mdh5vmfy74svufgot/site.standard.document/3mhn5qhx2r2s2","publishedAt":"2026-03-22T08:00:00Z","tags":"Forbes Money;economizar;geopolítica;incerteza;incertezas políticas;Reserva de emergência;Como Repensar a Reserva de Emergência em Tempos de Incerteza na Geopolítica Global?;Forbes Brasil"}