{"title":"A Vast Trove of Exposed Social Security Numbers May Put Millions at Risk of Identity Theft","path":"/story/a-mega-trove-of-exposed-social-security-numbers-underscores-critical-identity-theft-risks/","site":"https://www.wired.com","atUri":"at://did:plc:ao3t7cr3n5vz5lhwlje3oied/site.standard.document/3mf5ncjj5crk2","publishedAt":"2026-02-18T17:22:10Z","tags":"Security;Security / Cyberattacks and Hacks;Security / Privacy;Security / Security News;cybersecurity;security;databases;data privacy;privacy;scams;Crime;Major Threat"}