{"title":"14 Murals That Change the Mood of a City","path":"/2026/04/03/murals-that-change-the-mood-of-a-city/","site":"https://streetartutopia.com","atUri":"at://did:plc:c6ke4dmsb7oos6mkjoapsimo/site.standard.document/3milud4b3baw2","publishedAt":"2026-04-03T13:07:57Z","tags":"real art-history roots;Made You Feel (10 Photos);SMOK;SMOK on Instagram;Studio Giftig describes it;Studio Giftig on Instagram;trompe l’oeil;Nego on Instagram;here;CNIM;Tom Wild Sketch;TETAL;4 Photos of Cats and Birds Mural by Alegria del Prado in Carballo, Spain;Alegría del Prado on Instagram;inks them to;Dan Kitchener on Instagram;Origami Fox by Annatomix in Longbridge, Birmingham (3 photos and video);can shrink to around 25 hectares;Annatomix on Instagram;Vinie’s Stunning Murals (25 Photos);Vinie on Instagram;The drunken ship (6 photos);The Drunken Ship;Mauritshuis Murals;Julien de Casabianca on Instagram;Bogdan Scutaru on Instagram;Maksim Sidorov on Instagram;Naomi Rozalina King on Instagram;8 Happy 3D Artworks by Jan Is De Man That Will Make You Smile;Jan Is De Man on Instagram"}