{"title":"È morta Giorgia Centofanti, figlia di Felice. La lettera della sorella Martina: “Speriamo di essere stati degni di te”","path":"/2026/04/04/centofanti-lutto-figlia-giorgia-notizie/8346329/","site":"https://www.ilfattoquotidiano.it","atUri":"at://did:plc:ythu5ecnpc3zl3m4gmzxdaul/site.standard.document/3mioun6q7jfx2","publishedAt":"2026-04-04T18:29:26Z","tags":"Calcio;Inter;È morta Giorgia Centofanti, figlia di Felice. La lettera della sorella Martina: “Speriamo di essere stati degni di te”;Il Fatto Quotidiano"}