{"title":"A scenic city with coastal charm is named among the UK's most peaceful holiday destinations","path":"/travel/most-peaceful-staycation-swansea-dundee-leeds","site":"https://www.gbnews.com","atUri":"at://did:plc:oznbnvgr7dmvddiyvr7dih52/site.standard.document/3megsvkq4ee52","publishedAt":"2026-02-09T14:51:08Z","tags":"A British spa city is named among the most welcoming in the world for a 2026 holiday - top 10;Nostalgic staycations to dominate this year as Britons return to their most-loved holiday spots;The most booked UK breaks for 2026 with 'natural beauty, unique experiences and a sense of escape';where to visit in January, February and March;The GB News Editorial Charter"}