{"title":"William Shatner slams AI fake news claiming he's dying, had heated Erika Kirk confrontation","path":"/entertainment/william-shatner-slams-ai-fake-news-claiming-hes-dying-heated-erika-kirk-confrontation","site":"https://www.foxnews.com","atUri":"at://did:plc:6pwit4ctv4egvys3qyqmgbi6/site.standard.document/3mim7ezjoff42","publishedAt":"2026-04-03T15:29:45Z","tags":"2f4fb6e0-70c5-5b33-94f2-07f76b1dde36;fnc;Fox News;fox-news/entertainment;fox-news/person/william-shatner;fox-news/entertainment/movies;fox-news/entertainment/tv;article"}