{"title":"US immigration court blocks deportation of Tufts graduate student from Turkey, her attorneys say","path":"/news/local-news/2026/02/10/us-immigration-court-blocks-deportation-tufts-graduate-student-turkey/","site":"https://www.boston.com","atUri":"at://did:plc:q2zmlz6xv3irw4lsczr7fgvv/site.standard.document/3mejatwpsqx52","publishedAt":"2026-02-10T14:57:37Z","tags":"News;Immigration;Local News;Massachusetts News;Tufts University;US immigration court blocks deportation of Tufts graduate student from Turkey, her attorneys say;Boston.com"}