{"title":"As some people push to make profound autism its own diagnosis, this Ayer family is raising twins with it","path":"/news/local-news/2026/02/15/as-some-people-push-to-make-profound-autism-its-own-diagnosis-this-ayer-family-is-raising-twins-with-it/","site":"https://www.boston.com","atUri":"at://did:plc:q2zmlz6xv3irw4lsczr7fgvv/site.standard.document/3mewhcwzkvia2","publishedAt":"2026-02-15T13:58:39Z","tags":"News;Health;Local News;As some people push to make profound autism its own diagnosis, this Ayer family is raising twins with it;Boston.com"}