{"title":"The Arboretum of the Grey Warlock is Out in PDF from Raging Swan Press","path":"/game-news/the-arboretum-of-the-grey-warlock-is-out-in-pdf-from-raging-swan-press","site":"https://thegaminggang.com","atUri":"at://did:plc:3w6onrhbti4btiia43aburim/site.standard.document/3meoisb6udlt2","publishedAt":"2026-02-12T11:20:06Z","tags":"Gaming News;RPGs;Tabletop Gaming;DriveThruRPG;Dungeons & Dragons;Languard Backdrop;Languard Backdrop Arboretum of the Grey Warlock;OSR;Raging Swan Press;Continue Reading The Arboretum of the Grey Warlock is Out in PDF from Raging Swan Press"}