{"title":"Durante décadas pensamos que evolucionar significaba volverse más complejo. Este diminuto caballito de mar demostró que, a veces, la mejor estrategia para sobrevivir era perder justo lo que parecía indispensable","path":"/durante-decadas-creimos-que-el-camuflaje-era-cuestion-de-ganar-complejidad-este-caballito-de-mar-mostro-que-perderla-fue-secreto-2000189520","site":"https://es.gizmodo.com","atUri":"at://did:plc:5ovpevcql62fs43duhethzix/site.standard.document/3miq4q5a3z6g2","publishedAt":"2026-04-04T22:03:46Z","tags":"Ciencia"}