{"title":"Carnaval 2026: Virginia Fonseca interrompe ensaio da Grande Rio ao ver as filhas e emociona o público","path":"/carnaval/carnaval-2026-virginia-fonseca-interrompe-ensaio-da-grande-rio-ao-ver-as-filhas-e-emociona-o-publico.phtml","site":"https://www.marciapiovesan.com.br","atUri":"at://did:plc:jmubj2ufwtu7csgtauzftwlg/site.standard.document/3mehb4pqmhat2","publishedAt":"2026-02-09T16:55:28Z","tags":"Carnaval;destaques;Famosos;Internet;Carnaval 2026;Carnaval Rio de Janeiro;Ensaio Técnico Grande Rio;Famosos no Carnaval;grande rio;Maria Alice e Maria Flor;rainha de bateria;Sapucaí 2026;virgínia fonseca;Virginia na Sapucaí;Carnaval 2026: Virginia Fonseca interrompe ensaio da Grande Rio ao ver as filhas e emociona o público;Márcia Piovesan"}