{"title":"‘F*** me, it’s going to carry on’: Peter Molyneux says he teared up watching Playground’s Fable reveal","path":"/news/f-me-its-going-to-carry-on-peter-molyneux-says-he-teared-up-watching-playgrounds-fable-reveal/","site":"https://www.videogameschronicle.com","atUri":"at://did:plc:vfjos7cfvylyjg5uemuxv27r/site.standard.document/3memobmaxqiz2","publishedAt":"2026-02-11T20:45:53Z","tags":"Uncategorized;‘F*** me, it’s going to carry on’: Peter Molyneux says he teared up watching Playground’s Fable reveal;CVG"}