{"title":"‘The attorney general did not tip us off’: Eric Swalwell flat-out denies Pam Bondi leaked to him, and points to who actually did","path":"/news/the-attorney-general-did-not-tip-us-off-eric-swalwell-flat-out-denies-pam-bondi-leaked-to-him-and-points-to-who-actually-did/","site":"https://wegotthiscovered.com","atUri":"at://did:plc:oumtuxlgxscefvenrhhc2xhz/site.standard.document/3minpjwbowyz2","publishedAt":"2026-04-03T20:40:44Z","tags":"News;Politics;Donald Trump;Eric Swalwell;Pam Bondi"}