{"title":"America is at war with Iran, and Pete Hegseth just fired 3 generals in a single day, including the Army’s top officer","path":"/news/america-is-at-war-with-iran-and-pete-hegseth-just-fired-3-generals-in-a-single-day-including-the-armys-top-officer/","site":"https://wegotthiscovered.com","atUri":"at://did:plc:oumtuxlgxscefvenrhhc2xhz/site.standard.document/3minpju2re4q2","publishedAt":"2026-04-03T20:40:46Z","tags":"News;Politics;David Hodne;Pete Hegseth;Randy George;Sean Parnell;William Green"}