{"title":"Bae In Hyuk And Roh Jeong Eui Radiate Warm Family Chemistry With Child Actor Behind The Scenes Of “Our Universe”","path":"/article/1818324wpp/bae-in-hyuk-and-roh-jeong-eui-radiate-warm-family-chemistry-with-child-actor-behind-the-scenes-of-our-universe","site":"https://www.soompi.com","atUri":"at://did:plc:vgir22ikdsbnpcf65dkxjqw2/site.standard.document/3megmlcx67ha2","publishedAt":"2026-02-09T11:49:15Z","tags":"Drama;TV/Film;Bae In Hyuk;drama;Ha Jun;Our Universe;Park Ji Hyun;Roh Jeong Eui;Continue reading Bae In Hyuk And Roh Jeong Eui Radiate Warm Family Chemistry With Child Actor Behind The Scenes Of “Our Universe”;Bae In Hyuk And Roh Jeong Eui Radiate Warm Family Chemistry With Child Actor Behind The Scenes Of “Our Universe”;Soompi"}