{"title":"Will AI Kill the OSS Star?","path":"/will-ai-kill-the-oss-star/","site":"https://devops.com","atUri":"at://did:plc:gapzbf5nl5wxaqkqoecaeawh/site.standard.document/3mei7iqxvmbf2","publishedAt":"2026-02-09T11:54:47Z","tags":"AI;Blogs;Business of DevOps;DevOps and Open Technologies;Features;News;Social - Facebook;Social - LinkedIn;Social - X;AI and OSS relationship;AI impact on open source;AI slop;AI-generated pull requests;apprenticeship model;coding ecosystem;collective understanding;community health;community interaction;custom code generation;documentation decline;economic shift;engagement drop;fragmentation risk;generative AI;licensing issues;long-term sustainability;open source challenges;open source maintenance;OSS market;software development trends;software security;standardization;technology evolution.;vibe coding"}