{"title":"Ayo Edebiri Is Her Own Canvas","path":"/ayo-edebiri-cover","site":"https://www.papermag.com","atUri":"at://did:plc:seei7jfrednvhget3jdm6pvy/site.standard.document/3midesoyjv4c2","publishedAt":"2026-03-30T14:00:42Z","tags":"The bear;Chanel;Don cheadle;Broadway;Tony awards;Ayo edebiri;Proof;CHANEL Beauty;Jaša Müller;Yohana Desta;Angelina Cantú;Dee Carrion;Jacob Aaron;Naoko Saita;Nicole Alvarenga;Quinn Tommy Herbert;Coco Emery;Madeline Julietta Davis;Brian Calle;Jordan Bradfield;Joan Summers"}